LICENSE
MANIFEST.in
README.rst
setup.py
steward/__init__.py
steward.egg-info/PKG-INFO
steward.egg-info/SOURCES.txt
steward.egg-info/dependency_links.txt
steward.egg-info/top_level.txt