Metadata-Version: 1.1
Name: steward
Version: 0.0.4
Summary: Library for easy converting between plain JSON-like data and compound structure of user defined class instances.
Home-page: https://github.com/asvetlov/steward
Author: Andrew Svetlov
Author-email: andrew.svetlov@gmail.com
License: MIT License
Platform: any
Classifier: Development Status :: 3 - Alpha
Classifier: Intended Audience :: Developers
Classifier: License :: OSI Approved :: MIT License
Classifier: Operating System :: OS Independent
Classifier: Programming Language :: Python :: 3
Classifier: Programming Language :: Python :: 3.2
Classifier: Programming Language :: Python :: 3.3
Classifier: Topic :: Software Development :: Libraries :: Python Modules
